scalebox/__init__.py
scalebox/cli.py
scalebox/connection_config.py
scalebox/exceptions.py
scalebox/requirements.txt
scalebox/version.py
scalebox/api/__init__.py
scalebox/api/metadata.py
scalebox/api/client/__init__.py
scalebox/api/client/client.py
scalebox/api/client/errors.py
scalebox/api/client/py.typed
scalebox/api/client/types.py
scalebox/api/client/api/__init__.py
scalebox/api/client/api/sandboxes/__init__.py
scalebox/api/client/api/sandboxes/delete_sandboxes_sandbox_id.py
scalebox/api/client/api/sandboxes/get_sandboxes.py
scalebox/api/client/api/sandboxes/get_sandboxes_metrics.py
scalebox/api/client/api/sandboxes/get_sandboxes_sandbox_id.py
scalebox/api/client/api/sandboxes/get_sandboxes_sandbox_id_logs.py
scalebox/api/client/api/sandboxes/get_sandboxes_sandbox_id_metrics.py
scalebox/api/client/api/sandboxes/get_v2_sandboxes.py
scalebox/api/client/api/sandboxes/post_sandboxes.py
scalebox/api/client/api/sandboxes/post_sandboxes_sandbox_id_pause.py
scalebox/api/client/api/sandboxes/post_sandboxes_sandbox_id_refreshes.py
scalebox/api/client/api/sandboxes/post_sandboxes_sandbox_id_resume.py
scalebox/api/client/api/sandboxes/post_sandboxes_sandbox_id_timeout.py
scalebox/api/client/models/__init__.py
scalebox/api/client/models/build_log_entry.py
scalebox/api/client/models/created_access_token.py
scalebox/api/client/models/created_team_api_key.py
scalebox/api/client/models/error.py
scalebox/api/client/models/identifier_masking_details.py
scalebox/api/client/models/listed_sandbox.py
scalebox/api/client/models/log_level.py
scalebox/api/client/models/new_access_token.py
scalebox/api/client/models/new_sandbox.py
scalebox/api/client/models/new_team_api_key.py
scalebox/api/client/models/node.py
scalebox/api/client/models/node_detail.py
scalebox/api/client/models/node_status.py
scalebox/api/client/models/node_status_change.py
scalebox/api/client/models/post_sandboxes_sandbox_id_refreshes_body.py
scalebox/api/client/models/post_sandboxes_sandbox_id_timeout_body.py
scalebox_sdk-0.1.25.dist-info/licenses/LICENSE
scalebox_sdk-0.1.25.dist-info/METADATA
scalebox_sdk-0.1.25.dist-info/WHEEL
scalebox_sdk-0.1.25.dist-info/entry_points.txt
scalebox_sdk-0.1.25.dist-info/top_level.txt
scalebox_sdk-0.1.25.dist-info/RECORD
