Metadata-Version: 2.4
Name: scalebox-sdk
Version: 0.1.25
Summary: ScaleBox Python SDK - A multi-language code execution sandbox with Python, R, Node.js, Deno/TypeScript, Java, and Bash support
Author-email: ScaleBox Team <dev@scalebox.dev>
Maintainer-email: ScaleBox Team <dev@scalebox.dev>
License: MIT
Project-URL: Homepage, https://github.com/scalebox-dev/scalebox-sdk-python
Project-URL: Documentation, https://docs.scalebox.dev/python-sdk
Project-URL: Repository, https://github.com/scalebox-dev/scalebox-sdk-python
Project-URL: Issues, https://github.com/scalebox-dev/scalebox-sdk-python/issues
Project-URL: Changelog, https://github.com/scalebox-dev/scalebox-sdk-python/blob/main/CHANGELOG.md
Keywords: sandbox,code-execution,multi-language,python,r,nodejs,typescript,java,bash
Classifier: Development Status :: 4 - Beta
Classifier: Intended Audience :: Developers
Classifier: Operating System :: OS Independent
Classifier: Programming Language :: Python :: 3
Classifier: Programming Language :: Python :: 3.10
Classifier: Programming Language :: Python :: 3.11
Classifier: Programming Language :: Python :: 3.12
Classifier: Programming Language :: Python :: 3.13
Classifier: Topic :: Software Development :: Libraries :: Python Modules
Classifier: Topic :: Software Development :: Testing
Classifier: Topic :: System :: Distributed Computing
Requires-Python: >=3.10
License-File: LICENSE
Requires-Dist: httpx>=0.24
Requires-Dist: aiohttp>=3.8.0
Requires-Dist: urllib3>=1.26.0
Requires-Dist: httpcore>=0.15.0
Requires-Dist: grpcio>=1.74.0
Requires-Dist: grpcio-tools>=1.74.0
Requires-Dist: protobuf>=4.21
Requires-Dist: connect-python<0.5.0,>=0.4.2
Requires-Dist: attrs>=21.4.0
Requires-Dist: dataclasses-json>=0.5.0
Requires-Dist: python-dateutil>=2.8.0
Requires-Dist: tenacity>=8.0.0
Requires-Dist: packaging>=21.0
Requires-Dist: typing-extensions>=4.0.0
Provides-Extra: dev
Requires-Dist: pytest>=7.0.0; extra == "dev"
Requires-Dist: pytest-asyncio>=0.21.0; extra == "dev"
Requires-Dist: pytest-cov>=4.0.0; extra == "dev"
Requires-Dist: black>=22.0.0; extra == "dev"
Requires-Dist: isort>=5.0.0; extra == "dev"
Requires-Dist: flake8>=4.0.0; extra == "dev"
Requires-Dist: mypy>=0.950; extra == "dev"
Requires-Dist: pre-commit>=2.17.0; extra == "dev"
Requires-Dist: python-dotenv>=0.19.0; extra == "dev"
Provides-Extra: docs
Requires-Dist: sphinx>=4.0.0; extra == "docs"
Requires-Dist: sphinx-rtd-theme>=1.0.0; extra == "docs"
Requires-Dist: myst-parser>=0.18.0; extra == "docs"
Dynamic: license-file
